fdb5lib/__init__.py
fdb5lib/bin/fdb
fdb5lib/bin/fdb-axes
fdb5lib/bin/fdb-copy
fdb5lib/bin/fdb-dump
fdb5lib/bin/fdb-dump-index
fdb5lib/bin/fdb-dump-toc
fdb5lib/bin/fdb-hide
fdb5lib/bin/fdb-info
fdb5lib/bin/fdb-inspect
fdb5lib/bin/fdb-list
fdb5lib/bin/fdb-lock
fdb5lib/bin/fdb-monitor
fdb5lib/bin/fdb-move
fdb5lib/bin/fdb-overlay
fdb5lib/bin/fdb-purge
fdb5lib/bin/fdb-read
fdb5lib/bin/fdb-reconsolidate-toc
fdb5lib/bin/fdb-reindex
fdb5lib/bin/fdb-root
fdb5lib/bin/fdb-schema
fdb5lib/bin/fdb-server
fdb5lib/bin/fdb-stats
fdb5lib/bin/fdb-status
fdb5lib/bin/fdb-unlock
fdb5lib/bin/fdb-where
fdb5lib/bin/fdb-which
fdb5lib/bin/fdb-wipe
fdb5lib/bin/fdb-write
fdb5lib/bin/grib2fdb5
fdb5lib/include/fdb5/LibFdb5.h
fdb5lib/include/fdb5/fdb5_config.h
fdb5lib/include/fdb5/fdb5_ecbuild_config.h
fdb5lib/include/fdb5/fdb5_version.h
fdb5lib/include/fdb5/api/DistFDB.h
fdb5lib/include/fdb5/api/FDB.h
fdb5lib/include/fdb5/api/FDBFactory.h
fdb5lib/include/fdb5/api/FDBStats.h
fdb5lib/include/fdb5/api/LocalFDB.h
fdb5lib/include/fdb5/api/RemoteFDB.h
fdb5lib/include/fdb5/api/SelectFDB.h
fdb5lib/include/fdb5/api/fdb_c.h
fdb5lib/include/fdb5/api/helpers/APIIterator.h
fdb5lib/include/fdb5/api/helpers/AxesIterator.h
fdb5lib/include/fdb5/api/helpers/Callback.h
fdb5lib/include/fdb5/api/helpers/ControlIterator.h
fdb5lib/include/fdb5/api/helpers/DumpIterator.h
fdb5lib/include/fdb5/api/helpers/FDBToolRequest.h
fdb5lib/include/fdb5/api/helpers/ListElement.h
fdb5lib/include/fdb5/api/helpers/ListIterator.h
fdb5lib/include/fdb5/api/helpers/LockIterator.h
fdb5lib/include/fdb5/api/helpers/MoveIterator.h
fdb5lib/include/fdb5/api/helpers/PurgeIterator.h
fdb5lib/include/fdb5/api/helpers/StatsIterator.h
fdb5lib/include/fdb5/api/helpers/StatusIterator.h
fdb5lib/include/fdb5/api/helpers/WipeIterator.h
fdb5lib/include/fdb5/api/local/AxesVisitor.h
fdb5lib/include/fdb5/api/local/ControlVisitor.h
fdb5lib/include/fdb5/api/local/DumpVisitor.h
fdb5lib/include/fdb5/api/local/ListVisitor.h
fdb5lib-5.19.0.9.dist-info/licenses/AUTHORS
fdb5lib-5.19.0.9.dist-info/licenses/LICENSE
fdb5lib-5.19.0.9.dist-info/METADATA
fdb5lib-5.19.0.9.dist-info/WHEEL
fdb5lib-5.19.0.9.dist-info/top_level.txt
fdb5lib-5.19.0.9.dist-info/RECORD
