Metadata-Version: 2.4
Name: fdb5lib
Version: 5.19.0.9
Summary: "fdb5lib"
Author: file: AUTHORS
License-File: LICENSE
License-File: AUTHORS
Requires-Dist: eckitlib==1.32.4.9
Requires-Dist: eccodeslib==2.45.1.9
Requires-Dist: metkitlib==1.16.0.9
Dynamic: license-file
Dynamic: requires-dist
